pyloghandlers/__init__.py
pyloghandlers/handles.py
pyloghandlers-0.0.1.dist-info/LICENSE
pyloghandlers-0.0.1.dist-info/METADATA
pyloghandlers-0.0.1.dist-info/WHEEL
pyloghandlers-0.0.1.dist-info/top_level.txt
pyloghandlers-0.0.1.dist-info/zip-safe
pyloghandlers-0.0.1.dist-info/RECORD
