Metadata-Version: 2.1
Name: pyloghandlers
Version: 0.0.1
Summary: A python log handler packages with supported Multi-process
Home-page: https://github.com/ugvibib/pyloghandlers
Author: ugvibib
Author-email: ugvibib@163.com
License: Apache License Version 2.0, January 2004
Keywords: logging pylog loghandlers
Platform: UNKNOWN
Classifier: 
Requires-Dist: portalocker (>=2.0.0)
